python_uuidv47
