Metadata-Version: 2.4
Name: python-uuidv47
Version: 1.0.8
Summary: High-performance UUIDv47 operations - encoding UUIDv7 into UUIDv4 facades
Author-email: Fatah Chan <ahmadfathallah89@gmail.com>
License-Expression: MIT
Project-URL: Homepage, https://github.com/FatahChan/python-uuidv47
Project-URL: Repository, https://github.com/FatahChan/python-uuidv47.git
Project-URL: Issues, https://github.com/FatahChan/python-uuidv47/issues
Keywords: uuid,uuidv7,uuidv47,cryptography,performance
Classifier: Intended Audience :: Developers
Classifier: Programming Language :: Python :: 3
Classifier: Programming Language :: Python :: 3.9
Classifier: Programming Language :: Python :: 3.10
Classifier: Programming Language :: Python :: 3.11
Classifier: Programming Language :: Python :: 3.12
Classifier: Programming Language :: C
Classifier: Topic :: Security :: Cryptography
Classifier: Topic :: Software Development :: Libraries :: Python Modules
Classifier: Operating System :: OS Independent
Requires-Python: >=3.9
License-File: LICENSE
Dynamic: license-file
